pytest_yapf3/__init__.py
pytest_yapf3-0.7.0.dist-info/LICENSE
pytest_yapf3-0.7.0.dist-info/METADATA
pytest_yapf3-0.7.0.dist-info/WHEEL
pytest_yapf3-0.7.0.dist-info/entry_points.txt
pytest_yapf3-0.7.0.dist-info/top_level.txt
pytest_yapf3-0.7.0.dist-info/RECORD
