Metadata-Version: 2.1
Name: pytest-yapf3
Version: 0.7.0
Summary: Validate your Python file format with yapf
Home-page: https://github.com/yanqd0/pytest-yapf3
Author: Yan QiDong
Author-email: yanqd0@outlook.com
License: MIT
Keywords: pytest,yapf
Platform: any
Classifier: Development Status :: 5 - Production/Stable
Classifier: Framework :: Pytest
Classifier: Intended Audience :: Developers
Classifier: Topic :: Software Development :: Testing
Classifier: Programming Language :: Python :: 3
Classifier: Operating System :: OS Independent
Classifier: License :: OSI Approved :: MIT License
Requires-Python: >=3.6
License-File: LICENSE
Requires-Dist: pytest (>=7)
Requires-Dist: yapf
